legosec/__init__.py
legosec/identity/__init__.py
legosec/identity/identity.py
legosec/sdk/__init__.py
legosec/sdk/sdk.py
legosec_sdk-0.1.1.dist-info/licenses/LICENSE
legosec_sdk-0.1.1.dist-info/METADATA
legosec_sdk-0.1.1.dist-info/WHEEL
legosec_sdk-0.1.1.dist-info/dependency_links.txt
legosec_sdk-0.1.1.dist-info/top_level.txt
legosec_sdk-0.1.1.dist-info/RECORD
